<?xml version="1.0" encoding="UTF-8"?>
<data>
    <week>
        <sunday>
            <item hour="0000-1600">essence</item>
        </sunday>
        <monday>
            <item hour="0000-1634">welove</item>
            <item hour="1650-1651">essence</item>
            <item hour="1651-2359">welove</item>
        </monday>
        <tuesday>
            <item hour="0000-2359">essence</item>
        </tuesday>
        <wednesday>
            <item hour="0000-2249">welove</item>
            <item hour="2249-2250">essence</item>
            <item hour="2250-2359">welove</item>
        </wednesday>
        <thursday>
            <item hour="0000-2359">essence</item>
        </thursday>
        <friday>
            <item hour="0000-2359">welove</item>
        </friday>
        <saturday>
            <item hour="0000-0128">essence</item>
            <item hour="0128-2359">welove</item>
        </saturday>
    </week>

    <programs>
        <welove>
            <name>We Love</name>
            <author>Paul Marok</author>
            <image>welove.png</image>
            <type>audio</type>
            <facebook>none</facebook>
            <twitter>none</twitter>
            <soundcloud>none</soundcloud>
            <youtube>none</youtube>
            <globalhouse>none</globalhouse>
            <description>Descripcion del programa de We Love con Paul Marok</description>
        </welove>
        <essence>
            <name>Marok Essence</name>
            <author>Paul Marok Essence</author>
            <image>essence.png</image>
            <type>video</type>
            <facebook>none</facebook>
            <twitter>none</twitter>
            <soundcloud>none</soundcloud>
            <youtube>none</youtube>
            <globalhouse>none</globalhouse>
            <description>Descripcion del programa de Marok Essence con Paul Marok Essence</description>
        </essence>
    </programs>

</data>


